ml_adapter/api/__init__.py
ml_adapter/api/py.typed
ml_adapter/api/types.py
ml_adapter/api/data/__init__.py
ml_adapter/api/data/common.py
ml_adapter/api/data/v1.py
ml_adapter/api/data/v2.py
waylay_ml_adapter_api-0.1.1.dist-info/licenses/LICENCE.txt
waylay_ml_adapter_api-0.1.1.dist-info/METADATA
waylay_ml_adapter_api-0.1.1.dist-info/WHEEL
waylay_ml_adapter_api-0.1.1.dist-info/top_level.txt
waylay_ml_adapter_api-0.1.1.dist-info/RECORD
