Metadata-Version: 2.4
Name: waylay-ml-adapter-api
Version: 0.1.1
Summary: API models for the ml-adapter.
Author-email: Waylay <info@waylay.io>
Requires-Python: >=3.11
License-File: LICENCE.txt
Provides-Extra: dev
Requires-Dist: waylay-ml-adapter-devtools; extra == "dev"
Dynamic: license-file
